selcuk_serverless_sdk/__init__.py
selcuk_serverless_sdk/base.py
selcuk_serverless_sdk/exceptions.py
selcuk_serverless_sdk/sdk/__init__.py
selcuk_serverless_sdk/sdk/base.py
selcuk_serverless_sdk/span/__init__.py
selcuk_serverless_sdk/span/id.py
selcuk_serverless_sdk/span/name.py
selcuk_serverless_sdk/span/tags.py
selcuk_serverless_sdk/span/trace.py
selcuk_serverless_sdk/tests/__init__.py
selcuk_serverless_sdk/tests/test_id.py
selcuk_serverless_sdk/tests/test_name.py
selcuk_serverless_sdk/tests/test_sdk.py
selcuk_serverless_sdk/tests/test_tags.py
selcuk_serverless_sdk/tests/test_trace_span.py
selcuk_serverless_sdk-0.0.4.dist-info/METADATA
selcuk_serverless_sdk-0.0.4.dist-info/WHEEL
selcuk_serverless_sdk-0.0.4.dist-info/top_level.txt
selcuk_serverless_sdk-0.0.4.dist-info/RECORD
